maskedautoencoder/__init__.py
maskedautoencoder/demo_mae.py
maskedautoencoder/engine_finetune.py
maskedautoencoder/engine_pretrain.py
maskedautoencoder/main_finetune.py
maskedautoencoder/main_linprobe.py
maskedautoencoder/main_pretrain.py
maskedautoencoder/models_mae.py
maskedautoencoder/models_vit.py
maskedautoencoder/submitit_finetune.py
maskedautoencoder/submitit_linprobe.py
maskedautoencoder/submitit_pretrain.py
maskedautoencoder-0.0.1.dist-info/LICENSE
maskedautoencoder-0.0.1.dist-info/METADATA
maskedautoencoder-0.0.1.dist-info/WHEEL
maskedautoencoder-0.0.1.dist-info/top_level.txt
maskedautoencoder-0.0.1.dist-info/RECORD
