Metadata-Version: 2.1
Name: maskedautoencoder
Version: 0.0.1
Summary: MAE - Masked Autoencoder (An Updated PyTorch Implementation for Single GPU with 4GB Memory)
Home-page: https://github.com/henrywoo/mae
Author: Fuheng Wu
Keywords: maskedautoencoder,mae,autoendcoder
Classifier: Programming Language :: Python :: 3
Classifier: Programming Language :: Python :: 3.8
Classifier: Programming Language :: Python :: 3.9
Classifier: Programming Language :: Python :: 3.10
Classifier: Programming Language :: Python :: 3.11
Classifier: Programming Language :: Python :: 3.12
Classifier: Programming Language :: Python :: 3.13
License-File: LICENSE
